[{"name":"Александр","surname":"Курочкин","lastName":"Викторович","contacts":[{"type":"Телефон","value":"88077756229"},{"type":"Email","value":"kurochkin@mail.ru"}],"id":"1676105174298","updatedAt":"2023-02-11T09:45:41.481Z","createdAt":"2023-02-11T08:46:14.298Z"},{"name":"Даниил","surname":"Зубенко","lastName":"Андреевич","contacts":[{"type":"Телефон","value":"88005553535"}],"id":"1676275178636","updatedAt":"2023-02-13T07:59:38.636Z","createdAt":"2023-02-13T07:59:38.636Z"},{"name":"Иван","surname":"Иванов","lastName":"Андреевич","contacts":[{"type":"Email","value":"ivan@mail.ru"}],"id":"1676276776273","updatedAt":"2023-02-13T08:26:16.273Z","createdAt":"2023-02-13T08:26:16.273Z"}]